setup.py
gambit/__init__.py
gambit.egg-info/PKG-INFO
gambit.egg-info/SOURCES.txt
gambit.egg-info/dependency_links.txt
gambit.egg-info/pbr.json
gambit.egg-info/top_level.txt
gambit.egg-info/zip-safe