Metadata-Version: 1.0
Name: gambit
Version: 0.1.6
Summary: A micro library for performing multi queries in elasticsearch
Home-page: UNKNOWN
Author: Avichal Pandey
Author-email: pandeyavichal7@gmail.com
License: MIT License
Keywords: elasticsearch elastic
Platform: UNKNOWN
